mongoengine-stubs/__init__.pyi
mongoengine-stubs/common.pyi
mongoengine-stubs/connection.pyi
mongoengine-stubs/context_managers.pyi
mongoengine-stubs/dereference.pyi
mongoengine-stubs/document.pyi
mongoengine-stubs/errors.pyi
mongoengine-stubs/fields.pyi
mongoengine-stubs/mongodb_support.pyi
mongoengine-stubs/pymongo_support.pyi
mongoengine-stubs/signals.pyi
mongoengine-stubs/base/__init__.pyi
mongoengine-stubs/base/common.pyi
mongoengine-stubs/base/datastructures.pyi
mongoengine-stubs/base/document.pyi
mongoengine-stubs/base/fields.pyi
mongoengine-stubs/base/metaclasses.pyi
mongoengine-stubs/base/utils.pyi
mongoengine-stubs/queryset/__init__.pyi
mongoengine-stubs/queryset/base.pyi
mongoengine-stubs/queryset/field_list.pyi
mongoengine-stubs/queryset/manager.pyi
mongoengine-stubs/queryset/queryset.pyi
mongoengine-stubs/queryset/transform.pyi
mongoengine-stubs/queryset/visitor.pyi
mongoengine_stubs-0.24.0.dist-info/METADATA
mongoengine_stubs-0.24.0.dist-info/WHEEL
mongoengine_stubs-0.24.0.dist-info/top_level.txt
mongoengine_stubs-0.24.0.dist-info/RECORD
